[{"content":"This is an example renovated on 17/03/2023\n","permalink":"https://blog.oscarizval.com/posts/test/","summary":"This is an example renovated on 17/03/2023","title":"TestPost"},{"content":"Hey there! 👋 I\u0026rsquo;m Óscar Welcome to my Digital Atlantis, where I basically post what I would normally do offline, for the sake of keeping track of things. I work as an SRE/DevOps but I\u0026rsquo;m also interested in personal finances and investing. In my free time you can find me doing Track \u0026amp; Field or shamelessly assaulting a sushi place for dinner 🍣.\nI\u0026rsquo;d be more than happy to hear from you in case you have any feedback so here\u0026rsquo;s my LinkedIn profile.\n","permalink":"https://blog.oscarizval.com/about/","summary":"Hey there! 👋 I\u0026rsquo;m Óscar Welcome to my Digital Atlantis, where I basically post what I would normally do offline, for the sake of keeping track of things. I work as an SRE/DevOps but I\u0026rsquo;m also interested in personal finances and investing. In my free time you can find me doing Track \u0026amp; Field or shamelessly assaulting a sushi place for dinner 🍣.\nI\u0026rsquo;d be more than happy to hear from you in case you have any feedback so here\u0026rsquo;s my LinkedIn profile.","title":"About me"}]